README.txt
setup.py
docs/HISTORY.txt
docs/LICENSE.ZPL
five/__init__.py
five.caching.egg-info/PKG-INFO
five.caching.egg-info/SOURCES.txt
five.caching.egg-info/dependency_links.txt
five.caching.egg-info/namespace_packages.txt
five.caching.egg-info/not-zip-safe
five.caching.egg-info/requires.txt
five.caching.egg-info/top_level.txt
five/caching/__init__.py
five/caching/configure.zcml
five/caching/event.py
five/caching/modified.py