Metadata-Version: 1.0
Name: five.caching
Version: 1.0
Summary: Zope2 integration for z3c.caching
Home-page: http://pypi.python.org/pypi/five.caching
Author: Wichert Akkerman
Author-email: wichert@wiggy.net
License: ZPL
Platform: UNKNOWN
Classifier: Environment :: Web Environment
Classifier: Framework :: Plone
Classifier: Programming Language :: Python
